mama/__init__.py
mama/_version.py
mama/artifactory.py
mama/build_config.py
mama/build_dependency.py
mama/build_target.py
mama/cmake_configure.py
mama/dependency_chain.py
mama/init_project.py
mama/main.py
mama/msbuild.py
mama/package.py
mama/papa_deploy.py
mama/papa_upload.py
mama/parse_mamafile.py
mama/util.py
mama/platforms/__init__.py
mama/platforms/android.py
mama/platforms/mips.py
mama/platforms/oclea.py
mama/types/__init__.py
mama/types/artifactory_pkg.py
mama/types/asset.py
mama/types/dep_source.py
mama/types/git.py
mama/types/local_source.py
mama/utils/__init__.py
mama/utils/gdb.py
mama/utils/gnu_project.py
mama/utils/gtest.py
mama/utils/nonblocking_io.py
mama/utils/run.py
mama/utils/sub_process.py
mama/utils/system.py
mama-0.9.20.dist-info/licenses/LICENSE
mama-0.9.20.dist-info/METADATA
mama-0.9.20.dist-info/WHEEL
mama-0.9.20.dist-info/entry_points.txt
mama-0.9.20.dist-info/top_level.txt
mama-0.9.20.dist-info/RECORD
