Metadata-Version: 2.4
Name: mama
Version: 0.9.20
Summary: A modular C++ build tool even your mama can use
Author-email: Jorma Rebane <jorma.rebane@gmail.com>
License-Expression: MIT
Project-URL: Homepage, https://github.com/RedFox20/Mama
Project-URL: Bug Tracker, https://github.com/RedFox20/Mama/issues
Keywords: mama,build,mamabuild,c,c++,tool,cmake,simple,easy,package,manager,cross-platform
Classifier: Development Status :: 3 - Alpha
Classifier: Intended Audience :: Developers
Classifier: Topic :: Software Development :: Build Tools
Classifier: Programming Language :: Python :: 3
Classifier: Programming Language :: Python :: 3.6
Classifier: Operating System :: OS Independent
Requires-Python: >=3.6
License-File: LICENSE
Requires-Dist: distro
Requires-Dist: keyring
Requires-Dist: keyrings.cryptfile
Requires-Dist: termcolor
Requires-Dist: colorama
Requires-Dist: python-dateutil
Requires-Dist: psutil
Dynamic: license-file
